hidetext/__init__.py
hidetext/censor.py
hidetext/filters/__init__.py
hidetext/filters/email.py
hidetext/filters/filter.py
hidetext/filters/id_card.py
hidetext/filters/pattern_filter.py
hidetext/filters/phone.py
hidetext/filters/profanity.py
hidetext/hidetext.py
hidetext/placeholders/__init__.py
hidetext/placeholders/character.py
hidetext/placeholders/kind.py
hidetext/placeholders/placeholder.py
hidetext/resources/__init__.py
hidetext/resources/ca/__init__.py
hidetext/resources/ca/profanities.txt
hidetext/resources/en/__init__.py
hidetext/resources/en/profanities.txt
hidetext/textspan.py
hidetext-0.1.1.dist-info/LICENSE
hidetext-0.1.1.dist-info/WHEEL
hidetext-0.1.1.dist-info/METADATA
hidetext-0.1.1.dist-info/RECORD
