Metadata-Version: 2.1
Name: hidetext
Version: 0.1.1
Summary: Hides non-desired text
Home-page: https://github.com/jaume-ferrarons/hidetext
License: MIT
Keywords: text,filter,word,pattern
Author: Jaume Ferrarons
Author-email: jaume.ferrarons@gmail.com
Requires-Python: >=3.8.1,<4.0.0
Classifier: License :: OSI Approved :: MIT License
Classifier: Programming Language :: Python :: 3
Classifier: Programming Language :: Python :: 3.10
Classifier: Programming Language :: Python :: 3.9
Project-URL: Repository, https://github.com/jaume-ferrarons/hidetext
